aimem/__init__.py
aimem-0.0.1rc2.dist-info/METADATA
aimem-0.0.1rc2.dist-info/WHEEL
aimem-0.0.1rc2.dist-info/RECORD
