Metadata-Version: 2.1
Name: aimem
Version: 0.0.1rc2
Summary: The langmem alpha SDK
License: MIT
Author: William Fu-Hinthorn
Author-email: 13333726+hinthornw@users.noreply.github.com
Requires-Python: >=3.8,<4.0
Classifier: License :: OSI Approved :: MIT License
Classifier: Programming Language :: Python :: 3
Classifier: Programming Language :: Python :: 3.8
Classifier: Programming Language :: Python :: 3.9
Classifier: Programming Language :: Python :: 3.10
Classifier: Programming Language :: Python :: 3.11
Requires-Dist: httpx (>=0.26.0,<0.27.0)
Requires-Dist: pydantic (>=2.6.1,<3.0.0)
